_rig_c_sa.pyd
rig_c_sa/__init__.py
rig_c_sa/cffi_compile.py
rig_c_sa/sa.c
rig_c_sa/sa.h
rig_c_sa/version.py
rig_c_sa/usort/defs.c
rig_c_sa/usort/u1_sort.c
rig_c_sa/usort/u1_sort.h
rig_c_sa-0.4.0.dist-info/DESCRIPTION.rst
rig_c_sa-0.4.0.dist-info/METADATA
rig_c_sa-0.4.0.dist-info/RECORD
rig_c_sa-0.4.0.dist-info/WHEEL
rig_c_sa-0.4.0.dist-info/metadata.json
rig_c_sa-0.4.0.dist-info/top_level.txt
