Metadata-Version: 2.0
Name: rig-c-sa
Version: 0.4.0
Summary: A C library (and CFFI Python Interface) for simulated annealing.
Home-page: https://github.com/project-rig/rig_c_sa
Author: The Rig Authors
Author-email: UNKNOWN
License: GPLv2
Keywords: spinnaker placement cffi simulated-annealing
Platform: UNKNOWN
Classifier: Development Status :: 3 - Alpha
Classifier: Intended Audience :: Developers
Classifier: Intended Audience :: Science/Research
Classifier: License :: OSI Approved :: GNU General Public License v2 (GPLv2)
Classifier: Operating System :: POSIX :: Linux
Classifier: Operating System :: Microsoft :: Windows
Classifier: Operating System :: MacOS
Classifier: Programming Language :: Python :: 2
Classifier: Programming Language :: Python :: 2.7
Classifier: Programming Language :: Python :: 3
Classifier: Programming Language :: Python :: 3.4
Classifier: Programming Language :: Python :: 3.5
Classifier: Topic :: Software Development :: Libraries
Requires-Dist: cffi (>=1.0.0)
